vonixsync/__init__.py
vonixsync/api/__init__.py
vonixsync/api/api_request.py
vonixsync/configs/__init__.py
vonixsync/configs/base.py
vonixsync/configs/connection.py
vonixsync/configs/user_configs.py
vonixsync/entities/__init__.py
vonixsync/entities/agent.py
vonixsync/entities/agent_event.py
vonixsync/entities/agent_pause.py
vonixsync/entities/agent_summary.py
vonixsync/entities/call.py
vonixsync/entities/call_rating.py
vonixsync/entities/chat.py
vonixsync/entities/chat_message.py
vonixsync/entities/profiler.py
vonixsync/entities/queue.py
vonixsync/entities/queue_summary.py
vonixsync/entities/tree.py
vonixsync/main/__init__.py
vonixsync/main/create_database.py
vonixsync/main/syncronizer.py
vonixsync/mediators/__init__.py
vonixsync/mediators/agent_event_mediator.py
vonixsync/mediators/agent_mediator.py
vonixsync/mediators/agent_pause_mediator.py
vonixsync/mediators/agent_summary_mediator.py
vonixsync/mediators/call_mediator.py
vonixsync/mediators/chat_mediator.py
vonixsync/mediators/queue_mediator.py
vonixsync/mediators/queue_summary_mediator.py
vonixsync/repository/__init__.py
vonixsync/repository/agent_event_repository.py
vonixsync/repository/agent_pause_repository.py
vonixsync/repository/agent_repository.py
vonixsync/repository/agent_summary_repository.py
vonixsync/repository/call_rating_repository.py
vonixsync/repository/call_repository.py
vonixsync/repository/chat_message_repository.py
vonixsync/repository/chat_repository.py
vonixsync/repository/profilers_repository.py
vonixsync/repository/queue_repository.py
vonixsync/repository/queue_summary_repository.py
vonixsync/repository/tree_repository.py
vonixsync/utils/__init__.py
vonixsync/utils/errorHandler.py
vonixsync/utils/exception_classes.py
vonixsync-1.0.12.dist-info/LICENCE
vonixsync-1.0.12.dist-info/METADATA
vonixsync-1.0.12.dist-info/WHEEL
vonixsync-1.0.12.dist-info/top_level.txt
vonixsync-1.0.12.dist-info/RECORD
