Metadata-Version: 2.1
Name: vonixsync
Version: 1.0.12
Summary: Database syncronizer
Author-email: Victor Leone <victor@vonix.com>
Maintainer-email: Luiz <luiz@vonix.com.br>, Vonix <contato@vonix.com.br>
Project-URL: repository, https://github.com/vonix/vonix-py-sync
Keywords: syncronizer,vonix
Classifier: Programming Language :: Python :: 3
Classifier: Development Status :: 4 - Beta
Classifier: Environment :: MacOS X
Requires-Python: >=3.9
License-File: LICENCE
Requires-Dist: requests (>=2.28.2)
Requires-Dist: SQLAlchemy (>=2.0.6)
Requires-Dist: asyncpg (>=0.27.0)
Requires-Dist: psycopg2-binary (>=2.9.5)
Requires-Dist: aiohttp (>=3.8.4)
Requires-Dist: PyJWT (>=2.6.0)
Requires-Dist: mysql-connector-python (>=8.0.32)
